duckduckgo.py
duckduckgo3-0.242.dist-info/DESCRIPTION.rst
duckduckgo3-0.242.dist-info/METADATA
duckduckgo3-0.242.dist-info/RECORD
duckduckgo3-0.242.dist-info/WHEEL
duckduckgo3-0.242.dist-info/entry_points.txt
duckduckgo3-0.242.dist-info/metadata.json
duckduckgo3-0.242.dist-info/top_level.txt
