Metadata-Version: 2.0
Name: duckduckgo3
Version: 0.242
Summary: Library for querying the DuckDuckGo API
Home-page: http://github.com/crazedpsyc/python-duckduckgo/
Author: Michael Smith
Author-email: crazedpsyc@duckduckgo.com
License: BSD
Platform: any
Classifier: Development Status :: 4 - Beta
Classifier: Intended Audience :: Developers
Classifier: License :: OSI Approved :: BSD License
Classifier: Operating System :: OS Independent
Classifier: Programming Language :: Python
Classifier: Topic :: Internet :: WWW/HTTP :: Indexing/Search
